{
  "buildx.build.provenance": {
    "buildType": "https://mobyproject.org/buildkit@v1",
    "materials": [
      {
        "uri": "pkg:docker/kubeovn/kube-ovn-base@v1.13.0?platform=linux%2Famd64",
        "digest": {
          "sha256": "397cab7d540326c237afd2dc7b45bb976c7fafb61ff4d3a47d18f3334fd6c5a9"
        }
      },
      {
        "uri": "pkg:docker/golang@1.22-bookworm?platform=linux%2Famd64",
        "digest": {
          "sha256": "af9b40f2b1851be993763b85288f8434af87b5678af04355b1e33ff530b5765f"
        }
      }
    ],
    "invocation": {
      "configSource": {
        "entryPoint": "Dockerfile"
      },
      "parameters": {
        "frontend": "dockerfile.v0",
        "locals": [
          {
            "name": "context"
          },
          {
            "name": "dockerfile"
          }
        ]
      },
      "environment": {
        "platform": "linux/amd64"
      }
    }
  },
  "buildx.build.ref": "my-builder/my-builder0/woitxtz123n1x32p9mjkx5w1t",
  "containerimage.config.digest": "sha256:b5b30eebbe291534f0c6428de8d5effcb493e0b3a6dcd17f92c58036d901bb34",
  "containerimage.descriptor": {
    "mediaType": "application/vnd.docker.distribution.manifest.v2+json",
    "digest": "sha256:076c3c832ceb693d933d3ec067607ba0dcbba2cc842b92fbe76d8f84cb438938",
    "size": 4627,
    "platform": {
      "architecture": "amd64",
      "os": "linux"
    }
  },
  "containerimage.digest": "sha256:076c3c832ceb693d933d3ec067607ba0dcbba2cc842b92fbe76d8f84cb438938",
  "image.name": "ghcr.io/astrasky-net/kubeovn:v1.13.0,ghcr.io/astrasky-net/kubeovn:v1.13.0-v1.0.0"
}