{
  "buildx.build.provenance": {
    "buildType": "https://mobyproject.org/buildkit@v1",
    "materials": [
      {
        "uri": "pkg:docker/quay.io/poseidon/matchbox@v0.10.0?platform=linux%2Famd64",
        "digest": {
          "sha256": "e14cc4a8f6e8f1182fce74d04fe949b6bfc91b04132b3944297661e2c38c9790"
        }
      }
    ],
    "invocation": {
      "configSource": {
        "entryPoint": "Dockerfile"
      },
      "parameters": {
        "frontend": "dockerfile.v0",
        "locals": [
          {
            "name": "context"
          },
          {
            "name": "dockerfile"
          }
        ]
      },
      "environment": {
        "platform": "linux/amd64"
      }
    }
  },
  "buildx.build.ref": "my-builder/my-builder0/t5od3fm2chb6xegdo3j41f03e",
  "containerimage.config.digest": "sha256:249b271efabafaaddca12255859d7e07c80a7922255f345ebaf482b16b9488fc",
  "containerimage.descriptor": {
    "mediaType": "application/vnd.docker.distribution.manifest.v2+json",
    "digest": "sha256:a88002bc3e702ec1c2d452a0f92d3f5b805c348a9c22128c726e4a85c164a04b",
    "size": 1488,
    "platform": {
      "architecture": "amd64",
      "os": "linux"
    }
  },
  "containerimage.digest": "sha256:a88002bc3e702ec1c2d452a0f92d3f5b805c348a9c22128c726e4a85c164a04b",
  "image.name": "ghcr.io/astrasky-net/matchbox:v1.0.0,ghcr.io/astrasky-net/matchbox:v1.7.5-v1.0.0"
}